[
  {
    "id": "id1",
    "details": "jankoo   oaoaoa oaoaoa"
  },
  {
    "id": "id2",
    "details": "jankoo   oaoaoa oaoaoa"
  },
  {
    "id": "id3",
    "details": "jankoo   oaoaoa oaoaoa"
  },
  {
    "id": "id4",
    "details": "jankoo   oaoaoa oaoaoa"
  },
  {
    "id": "id5",
    "details": "jankoo   oaoaoa oaoaoa"
  },
  {
    "id": "id6",
    "details": "jankoo   oaoaoa oaoaoa"
  },
  {
    "id": "id7",
    "details": "jankoo   oaoaoa oaoaoa"
  },
  {
    "id": "id8",
    "details": "jankoo   oaoaoa oaoaoa"
  },
  {
    "id": "id9",
    "details": "jankoo   oaoaoa oaoaoa"
  },
  {
    "id": "id10",
    "details": "jankoo   oaoaoa oaoaoa"
  },
  {
    "id": "id11",
    "details": "jankoo   oaoaoa oaoaoa"
  },
  {
    "id": "id12",
    "details": "jankoo   oaoaoa oaoaoa"
  }
]
